MANIFEST.in
README.md
setup.cfg
setup.py
mark_utils/__init__.py
mark_utils/color.py
mark_utils/pca.py
mark_utils/pcap.py
mark_utils/preprocessing.py
mark_utils/scraper.py
mark_utils/text.py
mark_utils/time.py
mark_utils.egg-info/PKG-INFO
mark_utils.egg-info/SOURCES.txt
mark_utils.egg-info/dependency_links.txt
mark_utils.egg-info/top_level.txt
mark_utils/web_driver/geckodriver