Metadata-Version: 1.0
Name: mark-utils
Version: 0.1.94
Summary: Some Utils
Home-page: https://github.com/MarkNo1/Utils
Author: Marco Treglia
Author-email: marcotreglia1@gmail.com
License: BSD
Platform: any
